amaze/__init__.py
amaze/bin/__init__.py
amaze/bin/main.py
amaze/bin/tools/__init__.py
amaze/bin/tools/interpolator.py
amaze/bin/tools/stats.py
amaze/extensions/__init__.py
amaze/extensions/sb3/__init__.py
amaze/extensions/sb3/callbacks.py
amaze/extensions/sb3/controller.py
amaze/extensions/sb3/graph.py
amaze/extensions/sb3/guard.py
amaze/extensions/sb3/maze_env.py
amaze/extensions/sb3/networks.py
amaze/extensions/sb3/utils.py
amaze/misc/__init__.py
amaze/misc/resources.py
amaze/misc/utils.py
amaze/misc/plotters/__init__.py
amaze/misc/plotters/tabular.py
amaze/simu/__init__.py
amaze/simu/_build_data.py
amaze/simu/_inputs_evaluation.py
amaze/simu/_maze_metrics.py
amaze/simu/maze.py
amaze/simu/pos.py
amaze/simu/robot.py
amaze/simu/simulation.py
amaze/simu/types.py
amaze/simu/controllers/__init__.py
amaze/simu/controllers/base.py
amaze/simu/controllers/cheater.py
amaze/simu/controllers/control.py
amaze/simu/controllers/keyboard.py
amaze/simu/controllers/random.py
amaze/simu/controllers/tabular.py
amaze/visu/__init__.py
amaze/visu/maze.py
amaze/visu/viewer.py
amaze/visu/widgets/__init__.py
amaze/visu/widgets/_trajectory_plotter.py
amaze/visu/widgets/collapsible.py
amaze/visu/widgets/combobox.py
amaze/visu/widgets/labels.py
amaze/visu/widgets/lists.py
amaze/visu/widgets/maze.py
amaze_benchmarker-1.0.dist-info/licenses/LICENSE
amaze_benchmarker-1.0.dist-info/METADATA
amaze_benchmarker-1.0.dist-info/WHEEL
amaze_benchmarker-1.0.dist-info/entry_points.txt
amaze_benchmarker-1.0.dist-info/top_level.txt
amaze_benchmarker-1.0.dist-info/RECORD
