Metadata-Version: 2.4
Name: amaze-benchmarker
Version: 1.0
Summary: Benchmark generator for sighted maze-navigating agents
Author-email: Kevin Godin-Dubois <k.j.m.godin-dubois@vu.nl>
Project-URL: Homepage, https://github.com/kgd-al/amaze
Project-URL: Documentation, https://amaze.readthedocs.io/
Project-URL: Bug Tracker, https://github.com/kgd-al/amaze/issues
Classifier: Development Status :: 3 - Alpha
Classifier: Programming Language :: Python :: 3 :: Only
Classifier: License :: OSI Approved :: MIT License
Classifier: Operating System :: Unix
Classifier: Intended Audience :: Science/Research
Classifier: Topic :: Scientific/Engineering :: Artificial Intelligence
Classifier: Topic :: Scientific/Engineering :: Artificial Life
Requires-Python: >=3.8
License-File: LICENSE
Requires-Dist: numpy<2.0.0
Requires-Dist: pandas
Requires-Dist: PyQt5
Provides-Extra: sb3
Requires-Dist: stable_baselines3; extra == "sb3"
Requires-Dist: tensorboard; extra == "sb3"
Requires-Dist: graphviz; extra == "sb3"
Provides-Extra: full
Requires-Dist: amaze-benchmarker[sb3]; extra == "full"
Provides-Extra: tests
Requires-Dist: amaze-benchmarker; extra == "tests"
Requires-Dist: pytest; extra == "tests"
Requires-Dist: pytest-steps; extra == "tests"
Requires-Dist: pytest-sugar; extra == "tests"
Requires-Dist: pytest-qt; extra == "tests"
Requires-Dist: coverage; extra == "tests"
Requires-Dist: flake8; extra == "tests"
Requires-Dist: flake8-bugbear; extra == "tests"
Requires-Dist: flake8-pyproject; extra == "tests"
Requires-Dist: black; extra == "tests"
Requires-Dist: psutil; extra == "tests"
Requires-Dist: tabulate; extra == "tests"
Provides-Extra: docs
Requires-Dist: amaze-benchmarker[full]; extra == "docs"
Requires-Dist: sphinx<7.4.0; extra == "docs"
Requires-Dist: sphinx-pyproject; extra == "docs"
Requires-Dist: sphinx-qt-documentation; extra == "docs"
Requires-Dist: sphinx-copybutton; extra == "docs"
Requires-Dist: myst-parser; extra == "docs"
Requires-Dist: furo; extra == "docs"
Provides-Extra: dev
Requires-Dist: amaze-benchmarker[docs,full,tests]; extra == "dev"
Dynamic: license-file
